setup.py
keyuri/__init__.py
keyuri.egg-info/PKG-INFO
keyuri.egg-info/SOURCES.txt
keyuri.egg-info/dependency_links.txt
keyuri.egg-info/not-zip-safe
keyuri.egg-info/top_level.txt