Metadata-Version: 1.1
Name: keyuri
Version: 0.0.0
Summary: A URI-based format for encoding cryptographic keys
Home-page: https://github.com/miscreant/keyuri
Author: Tony Arcieri
Author-email: bascule@gmail.com
License: MIT license
Keywords: cryptography,security
Platform: UNKNOWN
Classifier: Development Status :: 2 - Pre-Alpha
Classifier: Intended Audience :: Developers
Classifier: License :: OSI Approved :: MIT License
Classifier: Natural Language :: English
